{
  "settings": {
    "migrated": 6,
    "iconPacksPath": ".obsidian/icons",
    "fontSize": 16,
    "emojiStyle": "native",
    "iconColor": null,
    "recentlyUsedIcons": [
      "LiDatabaseZap",
      "LiDice6",
      "LiAxis3d",
      "LiAreaChart",
      "LiPenTool"
    ],
    "recentlyUsedIconsSize": 5,
    "rules": [],
    "extraMargin": {
      "top": 0,
      "right": 4,
      "bottom": 0,
      "left": 0
    },
    "iconInTabsEnabled": false,
    "iconInTitleEnabled": false,
    "iconInTitlePosition": "above",
    "iconInFrontmatterEnabled": false,
    "iconInFrontmatterFieldName": "icon",
    "iconColorInFrontmatterFieldName": "iconColor",
    "iconsBackgroundCheckEnabled": false,
    "iconsInNotesEnabled": true,
    "iconsInLinksEnabled": true,
    "iconIdentifier": ":",
    "lucideIconPackType": "native",
    "debugMode": false,
    "useInternalPlugins": false
  },
  "Controle Estatístico do Processo": "LiSettings",
  "Probabilidade": "LiPercent",
  "Copilot Custom Prompts": "LiTextSelection",
  "Cálculo": "LiChartSpline",
  "Álgebra Linear": "LiAxis3d",
  "Métodos Numéricos": "🔢",
  "Excalidraw": "LiPenTool",
  "Estatística Básica": "LiAreaChart",
  "Análise de Dados": "LiDatabaseZap"
}